pysuerga/__init__.py
pysuerga/__main__.py
pysuerga/contrib/__init__.py
pysuerga/contrib/blog.py
pysuerga/contrib/navbar.py
pysuerga/contrib/releases.py
pysuerga/contrib/team.py
pysuerga/templates/layout.html
pysuerga-0.1.0.dist-info/LICENSE
pysuerga-0.1.0.dist-info/METADATA
pysuerga-0.1.0.dist-info/WHEEL
pysuerga-0.1.0.dist-info/top_level.txt
pysuerga-0.1.0.dist-info/RECORD
