Metadata-Version: 2.1
Name: pysuerga
Version: 0.1.0
Summary: Python simple static site generator for open source projects
Home-page: https://github.com/datapythonista/pysuerga
Author: Marc Garcia
Author-email: garcia.marc@gmail.com
License: BSD
Platform: UNKNOWN
Classifier: Development Status :: 4 - Beta
Classifier: Environment :: Console
Classifier: Operating System :: OS Independent
Classifier: Intended Audience :: Developers
Classifier: Programming Language :: Python :: 3
Classifier: Programming Language :: Python :: 3.6
Classifier: Programming Language :: Python :: 3.7
Classifier: Programming Language :: Python :: 3.8
Classifier: Topic :: Utilities
Requires-Dist: markdown
Requires-Dist: jinja2
Requires-Dist: pyyaml
